topsis_102303250/__init__.py
topsis_102303250/topsis.py
topsis_aishani_102303250-1.0.1.dist-info/licenses/LICENSE
topsis_aishani_102303250-1.0.1.dist-info/METADATA
topsis_aishani_102303250-1.0.1.dist-info/WHEEL
topsis_aishani_102303250-1.0.1.dist-info/entry_points.txt
topsis_aishani_102303250-1.0.1.dist-info/top_level.txt
topsis_aishani_102303250-1.0.1.dist-info/RECORD
