Metadata-Version: 2.4
Name: Topsis-Aishani-102303250
Version: 1.0.1
Summary: A Python package for TOPSIS implementation
Author-email: Aishani <aishani1020@gmail.com>
Project-URL: GitHub Repository, https://github.com/aishani-s20/TOPSIS_PYPI
Classifier: Programming Language :: Python :: 3
Classifier: License :: OSI Approved :: MIT License
Classifier: Operating System :: OS Independent
Requires-Python: >=3.6
License-File: LICENSE
Requires-Dist: pandas
Requires-Dist: numpy
Requires-Dist: scikit-learn
Dynamic: license-file
